easy_maps/__init__.py
easy_maps/admin.py
easy_maps/conf.py
easy_maps/geocode.py
easy_maps/models.py
easy_maps/utils.py
easy_maps/widgets.py
easy_maps/locale/de/LC_MESSAGES/django.mo
easy_maps/locale/de/LC_MESSAGES/django.po
easy_maps/locale/ru/LC_MESSAGES/django.mo
easy_maps/locale/ru/LC_MESSAGES/django.po
easy_maps/migrations/0001_initial.py
easy_maps/migrations/0002_auto_20190329_0541.py
easy_maps/migrations/0003_address_timestamp.py
easy_maps/migrations/__init__.py
easy_maps/templates/easy_maps/map.html
easy_maps/templatetags/__init__.py
easy_maps/templatetags/easy_maps_tags.py
easy_maps/tests/__init__.py
easy_maps/tests/conftest.py
easy_maps/tests/models.py
easy_maps/tests/settings.py
easy_maps/tests/test_templatetags.py
django_easy_maps-1.1.3.dist-info/AUTHORS
django_easy_maps-1.1.3.dist-info/LICENSE
django_easy_maps-1.1.3.dist-info/METADATA
django_easy_maps-1.1.3.dist-info/WHEEL
django_easy_maps-1.1.3.dist-info/top_level.txt
django_easy_maps-1.1.3.dist-info/RECORD
