Metadata-Version: 2.1
Name: django-easy-maps
Version: 1.1.3
Summary: This app makes it easy to display a map for a given address
Home-page: https://github.com/bashu/django-easy-maps
Author: Mikhail Korobov
Author-email: kmike84@gmail.com
Maintainer: Basil Shubin
Maintainer-email: basil.shubin@gmail.com
License: MIT License
Download-URL: https://github.com/bashu/django-easy-maps/zipball/master
Platform: UNKNOWN
Classifier: Development Status :: 5 - Production/Stable
Classifier: Environment :: Web Environment
Classifier: Intended Audience :: Developers
Classifier: License :: OSI Approved :: MIT License
Classifier: Operating System :: OS Independent
Classifier: Programming Language :: Python
Classifier: Programming Language :: Python :: 3 :: Only
Classifier: Programming Language :: Python :: 3.6
Classifier: Programming Language :: Python :: 3.7
Classifier: Programming Language :: Python :: 3.8
Classifier: Programming Language :: Python :: 3.9
Classifier: Framework :: Django
Classifier: Framework :: Django :: 2.2
Classifier: Framework :: Django :: 3.0
Classifier: Framework :: Django :: 3.1
Classifier: Framework :: Django :: 3.2
License-File: LICENSE
License-File: AUTHORS
Requires-Dist: django-classy-tags (>=0.6.2)
Requires-Dist: django-appconf
Requires-Dist: geopy (>=0.96)
Provides-Extra: develop
Requires-Dist: tox ; extra == 'develop'
Requires-Dist: mock ; extra == 'develop'
Requires-Dist: django ; extra == 'develop'
Requires-Dist: pytest-django ; extra == 'develop'
Requires-Dist: pytest ; extra == 'develop'
Provides-Extra: test
Requires-Dist: pytest-django ; extra == 'test'
Requires-Dist: pytest-cov ; extra == 'test'
Requires-Dist: pytest ; extra == 'test'
Requires-Dist: mock ; extra == 'test'
